stock/__init__.py
stock/stock_pb2.py
stock/stock_pb2_grpc.py
benproto-1.0.7.dist-info/LICENSE
benproto-1.0.7.dist-info/METADATA
benproto-1.0.7.dist-info/WHEEL
benproto-1.0.7.dist-info/top_level.txt
benproto-1.0.7.dist-info/RECORD
