Metadata-Version: 2.1
Name: benproto
Version: 1.0.7
Summary: for stock use grpc proto
Home-page: https://github.com/gobenpark
Author: benproto
Author-email: qjadn0914@naver.com
License: BSD 3-Clause License
Platform: UNKNOWN
Classifier: License :: OSI Approved :: BSD License
